{
  "aor": 0.0028667625899280575,
  "aqi": 0.0038589982733812952,
  "bids_meta": {
    "EchoTime": 0.25,
    "FlipAngle": 90,
    "InstitutionName": "University of Southern California",
    "Note": "First 3 TRs were removed",
    "RepetitionTime": 2.0,
    "SliceEncodingDirection": "i",
    "SliceTiming": [],
    "TaskName": "Spatial Detection",
    "dataset": "ds001242",
    "modality": "bold",
    "run_id": 3,
    "subject_id": "13",
    "task_id": "spatialdetection"
  },
  "dummy_trs": 0,
  "dvars_nstd": 13.8990999789855,
  "dvars_std": 1.1146517805072462,
  "dvars_vstd": 1.0115935329710144,
  "efc": 0.367335456827483,
  "fber": 11698.953125,
  "fd_mean": 0.05753842158736608,
  "fd_num": 3,
  "fd_perc": 2.158273381294964,
  "fwhm_avg": 1.9384125,
  "fwhm_x": 1.7737225,
  "fwhm_y": 2.077315,
  "fwhm_z": 1.9642,
  "gcor": 0.0867325,
  "gsr_x": -0.008170993067324162,
  "gsr_y": 0.01518232375383377,
  "provenance": {
    "md5sum": "5ea8ca6d47e11830500c2dd9ccd3acdc",
    "settings": {
      "fd_thres": 0.2,
      "testing": false
    },
    "software": "mriqc",
    "version": "22.0.1",
    "webapi_port": null,
    "webapi_url": "https://mriqc.nimh.nih.gov/api/v1"
  },
  "size_t": 139,
  "size_x": 64,
  "size_y": 64,
  "size_z": 41,
  "snr": 6.5592670667828115,
  "spacing_tr": 2.0,
  "spacing_x": 4.0,
  "spacing_y": 4.0,
  "spacing_z": 4.0,
  "summary_bg_k": 41.80497047672748,
  "summary_bg_mad": 5.866412042496605,
  "summary_bg_mean": 17.802757263183594,
  "summary_bg_median": 6.4820146560668945,
  "summary_bg_n": 124615.0,
  "summary_bg_p05": 1.3956835269927979,
  "summary_bg_p95": 70.8726646423339,
  "summary_bg_stdv": 36.209869384765625,
  "summary_fg_k": 1.6729380772275695,
  "summary_fg_mad": 83.52704358998321,
  "summary_fg_mean": 678.3966674804688,
  "summary_fg_median": 687.0935668945312,
  "summary_fg_n": 14433.0,
  "summary_fg_p05": 482.29640502929686,
  "summary_fg_p95": 828.9309692382811,
  "summary_fg_stdv": 104.7479476928711,
  "tsnr": 91.0648263230687
}