{
  "aor": 0.0074161151079136685,
  "aqi": 0.005347620071942446,
  "bids_meta": {
    "EchoTime": 0.25,
    "FlipAngle": 90,
    "InstitutionName": "University of Southern California",
    "Note": "First 3 TRs were removed",
    "RepetitionTime": 2.0,
    "SliceEncodingDirection": "i",
    "SliceTiming": [],
    "TaskName": "Spatial Detection",
    "dataset": "ds001242",
    "modality": "bold",
    "run_id": 3,
    "subject_id": "04",
    "task_id": "spatialdetection"
  },
  "dummy_trs": 0,
  "dvars_nstd": 18.59705033514493,
  "dvars_std": 1.2971016052898543,
  "dvars_vstd": 1.0697250587681155,
  "efc": 0.3909870724991884,
  "fber": 18360.0,
  "fd_mean": 0.07474860142097679,
  "fd_num": 4,
  "fd_perc": 2.8776978417266186,
  "fwhm_avg": 1.52885,
  "fwhm_x": 1.384625,
  "fwhm_y": 1.675135,
  "fwhm_z": 1.52679,
  "gcor": 0.061727,
  "gsr_x": -0.017827551811933517,
  "gsr_y": -0.004403647501021624,
  "provenance": {
    "md5sum": "90410d8e8ad4f5f79953fc862594ca47",
    "settings": {
      "fd_thres": 0.2,
      "testing": false
    },
    "software": "mriqc",
    "version": "22.0.1",
    "webapi_port": null,
    "webapi_url": "https://mriqc.nimh.nih.gov/api/v1"
  },
  "size_t": 139,
  "size_x": 64,
  "size_y": 64,
  "size_z": 41,
  "snr": 8.326677356336477,
  "spacing_tr": 2.0,
  "spacing_x": 4.0,
  "spacing_y": 4.0,
  "spacing_z": 4.0,
  "summary_bg_k": 31.40043603772755,
  "summary_bg_mad": 3.2425258666025747,
  "summary_bg_mean": 15.720697402954102,
  "summary_bg_median": 3.97841739654541,
  "summary_bg_n": 121356.0,
  "summary_bg_p05": 1.2230216264724731,
  "summary_bg_p95": 68.67086601257324,
  "summary_bg_stdv": 37.39484786987305,
  "summary_fg_k": 1.6366135844663559,
  "summary_fg_mad": 62.65858484862268,
  "summary_fg_mean": 529.2908325195312,
  "summary_fg_median": 528.1582641601562,
  "summary_fg_n": 16788.0,
  "summary_fg_p05": 435.1305755615234,
  "summary_fg_p95": 630.5532562255859,
  "summary_fg_stdv": 63.427764892578125,
  "tsnr": 89.92263318132609
}