{
  "aor": 0.001400431654676259,
  "aqi": 0.0018659354676258991,
  "bids_meta": {
    "EchoTime": 0.25,
    "FlipAngle": 90,
    "InstitutionName": "University of Southern California",
    "Note": "First 3 TRs were removed",
    "RepetitionTime": 2.0,
    "SliceEncodingDirection": "i",
    "SliceTiming": [],
    "TaskName": "Spatial Detection",
    "dataset": "ds001242",
    "modality": "bold",
    "run_id": 2,
    "subject_id": "15",
    "task_id": "spatialdetection"
  },
  "dummy_trs": 0,
  "dvars_nstd": 16.75703227724638,
  "dvars_std": 1.3061665888405785,
  "dvars_vstd": 1.0118953595652178,
  "efc": 0.37729089664000554,
  "fber": 18972.35546875,
  "fd_mean": 0.05536739299887055,
  "fd_num": 4,
  "fd_perc": 2.8776978417266186,
  "fwhm_avg": 1.9667833333333335,
  "fwhm_x": 1.7695775,
  "fwhm_y": 2.146475,
  "fwhm_z": 1.9842975,
  "gcor": 0.0543584,
  "gsr_x": -0.020715445280075073,
  "gsr_y": 0.008685256354510784,
  "provenance": {
    "md5sum": "4bdfca441fa2310904af07fefcbe58b8",
    "settings": {
      "fd_thres": 0.2,
      "testing": false
    },
    "software": "mriqc",
    "version": "22.0.1",
    "webapi_port": null,
    "webapi_url": "https://mriqc.nimh.nih.gov/api/v1"
  },
  "size_t": 139,
  "size_x": 64,
  "size_y": 64,
  "size_z": 41,
  "snr": 6.0586954987901755,
  "spacing_tr": 2.0,
  "spacing_x": 4.0,
  "spacing_y": 4.0,
  "spacing_z": 4.0,
  "summary_bg_k": 37.94853253799013,
  "summary_bg_mad": 4.586466928462598,
  "summary_bg_mean": 20.06971549987793,
  "summary_bg_median": 5.647481918334961,
  "summary_bg_n": 121980.0,
  "summary_bg_p05": 1.2589927911758423,
  "summary_bg_p95": 90.51834983825675,
  "summary_bg_stdv": 48.898887634277344,
  "summary_fg_k": 0.6632616016774335,
  "summary_fg_mad": 113.50974155545777,
  "summary_fg_mean": 759.8020629882812,
  "summary_fg_median": 766.6726684570312,
  "summary_fg_n": 16280.0,
  "summary_fg_p05": 529.2935424804688,
  "summary_fg_p95": 951.5165588378906,
  "summary_fg_stdv": 126.53699493408203,
  "tsnr": 113.01777924410999
}