{
  "aor": 0.00351568345323741,
  "aqi": 0.003747587266187051,
  "bids_meta": {
    "EchoTime": 0.25,
    "FlipAngle": 90,
    "InstitutionName": "University of Southern California",
    "Note": "First 3 TRs were removed",
    "RepetitionTime": 2.0,
    "SliceEncodingDirection": "i",
    "SliceTiming": [],
    "TaskName": "Spatial Detection",
    "dataset": "ds001242",
    "modality": "bold",
    "run_id": 4,
    "subject_id": "08",
    "task_id": "spatialdetection"
  },
  "dummy_trs": 0,
  "dvars_nstd": 16.93857649152174,
  "dvars_std": 1.2336526694202903,
  "dvars_vstd": 1.0168656820289856,
  "efc": 0.3922416348892788,
  "fber": 22946.91015625,
  "fd_mean": 0.0572863115966452,
  "fd_num": 6,
  "fd_perc": 4.316546762589928,
  "fwhm_avg": 1.6733533333333332,
  "fwhm_x": 1.51452,
  "fwhm_y": 1.798105,
  "fwhm_z": 1.707435,
  "gcor": 0.0415337,
  "gsr_x": -0.010820983909070492,
  "gsr_y": 0.008212381042540073,
  "provenance": {
    "md5sum": "b5fad7ed7c1eaebb79f99f8cba372255",
    "settings": {
      "fd_thres": 0.2,
      "testing": false
    },
    "software": "mriqc",
    "version": "22.0.1",
    "webapi_port": null,
    "webapi_url": "https://mriqc.nimh.nih.gov/api/v1"
  },
  "size_t": 139,
  "size_x": 64,
  "size_y": 64,
  "size_z": 41,
  "snr": 7.755569986249086,
  "spacing_tr": 2.0,
  "spacing_x": 4.0,
  "spacing_y": 4.0,
  "spacing_z": 4.0,
  "summary_bg_k": 34.20014163583021,
  "summary_bg_mad": 3.2531919462768895,
  "summary_bg_mean": 17.122936248779297,
  "summary_bg_median": 4.014388561248779,
  "summary_bg_n": 120495.0,
  "summary_bg_p05": 1.129496455192566,
  "summary_bg_p95": 82.0568367004392,
  "summary_bg_stdv": 42.890968322753906,
  "summary_fg_k": 1.4626648796714266,
  "summary_fg_mad": 70.35428938173976,
  "summary_fg_mean": 595.23681640625,
  "summary_fg_median": 595.161865234375,
  "summary_fg_n": 17250.0,
  "summary_fg_p05": 469.37662200927736,
  "summary_fg_p95": 715.6489288330077,
  "summary_fg_stdv": 76.73770141601562,
  "tsnr": 97.33779477328062
}