{
  "aor": 0.0039507909604519775,
  "aqi": 0.014441862316384179,
  "bids_meta": {
    "EchoTime": 0.25,
    "FlipAngle": 90,
    "InstitutionName": "University of Southern California",
    "Note": "First 3 TRs were removed",
    "RepetitionTime": 2.0,
    "SliceEncodingDirection": "i",
    "SliceTiming": [],
    "TaskName": "Fear Learning",
    "dataset": "ds001242",
    "modality": "bold",
    "subject_id": "46",
    "task_id": "fearlearning"
  },
  "dummy_trs": 0,
  "dvars_nstd": 30.183311976931805,
  "dvars_std": 1.1900960071022721,
  "dvars_vstd": 1.0168636934090909,
  "efc": 0.33627515903377964,
  "fber": 32494.66796875,
  "fd_mean": 0.14729898733486407,
  "fd_num": 38,
  "fd_perc": 21.468926553672315,
  "fwhm_avg": 1.4992975,
  "fwhm_x": 1.348915,
  "fwhm_y": 1.6091875,
  "fwhm_z": 1.53979,
  "gcor": 0.0392212,
  "gsr_x": -0.02543945051729679,
  "gsr_y": 0.014237175695598125,
  "provenance": {
    "md5sum": "5cf12cf8cec34c8110ffcbd7581a0592",
    "settings": {
      "fd_thres": 0.2,
      "testing": false
    },
    "software": "mriqc",
    "version": "22.0.1",
    "webapi_port": null,
    "webapi_url": "https://mriqc.nimh.nih.gov/api/v1"
  },
  "size_t": 177,
  "size_x": 64,
  "size_y": 64,
  "size_z": 41,
  "snr": 8.183918652981294,
  "spacing_tr": 2.0,
  "spacing_x": 4.0,
  "spacing_y": 4.0,
  "spacing_z": 4.0,
  "summary_bg_k": 71.23597488774097,
  "summary_bg_mad": 1.9432977162831877,
  "summary_bg_mean": 9.90019702911377,
  "summary_bg_median": 2.395480155944824,
  "summary_bg_n": 128242.0,
  "summary_bg_p05": 0.8531073331832886,
  "summary_bg_p95": 40.79011459350581,
  "summary_bg_stdv": 27.20549774169922,
  "summary_fg_k": 3.982959294138034,
  "summary_fg_mad": 43.54827298856985,
  "summary_fg_mean": 425.6695556640625,
  "summary_fg_median": 423.3559265136719,
  "summary_fg_n": 12017.0,
  "summary_fg_p05": 352.58531494140624,
  "summary_fg_p95": 509.41468505859365,
  "summary_fg_stdv": 51.72806930541992,
  "tsnr": 60.641532006673515
}